<?xml version="1.0" encoding="UTF-8"?>
<?xml-stylesheet type="text/xsl" href="configuration.xsl"?>
<!--
  Licensed under the Apache License, Version 2.0 (the "License");
  you may not use this file except in compliance with the License.
  You may obtain a copy of the License at

    http://www.apache.org/licenses/LICENSE-2.0

  Unless required by applicable law or agreed to in writing, software
  distributed under the License is distributed on an "AS IS" BASIS,
  WITHOUT WARRANTIES OR CONDITIONS OF ANY KIND, either express or implied.
  See the License for the specific language governing permissions and
  limitations under the License. See accompanying LICENSE file.
-->

<!-- Put site-specific property overrides in this file. -->

<configuration>

<property>
<!--指定hdfs保存数据副本的数量，包括自己，默认为3-->
<!--伪分布式模式，此值必须为1-->
<name>dfs.replication</name>
<value>1</value>
</property>

<!--不是root用户也可以写文件到hdfs-->
<property>
<name>dfs.permissions</name>
<value>false</value>    <!--关闭防火墙-->
</property>

</configuration>
